prometheus_salt_exporter/__init__.py
prometheus_salt_exporter/cli.py
prometheus_salt_exporter/collector.py
prometheus_salt_exporter/logger.py
prometheus_salt_exporter/main.py
prometheus_salt_exporter-0.1.4.dist-info/LICENSE
prometheus_salt_exporter-0.1.4.dist-info/METADATA
prometheus_salt_exporter-0.1.4.dist-info/WHEEL
prometheus_salt_exporter-0.1.4.dist-info/entry_points.txt
prometheus_salt_exporter-0.1.4.dist-info/top_level.txt
prometheus_salt_exporter-0.1.4.dist-info/RECORD
