Metadata-Version: 2.1
Name: prometheus-salt-exporter
Version: 0.1.4
Summary: Prometheus Exporter for Salt highstate metrics run from the Salt master.
Home-page: https://github.com/ioki-mobility/salt_exporter
Author: ioki SRE core
Author-email: sre.core@ioki.com
License: MIT
Keywords: prometheus exporter salt monitoring
Platform: UNKNOWN
Classifier: Development Status :: 3 - Alpha
Classifier: Intended Audience :: Information Technology
Classifier: Intended Audience :: System Administrators
Classifier: Topic :: System :: Monitoring
Classifier: Topic :: System :: Networking :: Monitoring
Classifier: License :: OSI Approved :: MIT License
Requires-Python: >=3.8
License-File: LICENSE
Requires-Dist: prometheus-client (>=0.16)
Requires-Dist: salt
